lu_project/__init__.py
ai_sci_exmaple-0.1.1.dist-info/METADATA
ai_sci_exmaple-0.1.1.dist-info/WHEEL
ai_sci_exmaple-0.1.1.dist-info/top_level.txt
ai_sci_exmaple-0.1.1.dist-info/RECORD
