Metadata-Version: 2.1
Name: ai-sci-exmaple
Version: 0.1.1
Requires-Dist: torch
